{
  "name": "Local",
  "faq": {
    "question": "What is the Anvil Composable Subsystem?",
    "answer": "Anvil Composable Subsystem is a Kubernetes based private cloud managed with Rancher that provides a platform for creating composable infrastructure on demand. This cloud-style flexibility provides researchers the ability to self-deploy and manage persistent services to complement HPC workflows and run container-based data analysis tools and applications.",
    "link": "https://www.rcac.purdue.edu/knowledge/anvil/composable"
  }
}
